azure/mgmt/containerservicesafeguards/__init__.py
azure/mgmt/containerservicesafeguards/_client.py
azure/mgmt/containerservicesafeguards/_configuration.py
azure/mgmt/containerservicesafeguards/_patch.py
azure/mgmt/containerservicesafeguards/_version.py
azure/mgmt/containerservicesafeguards/py.typed
azure/mgmt/containerservicesafeguards/_utils/__init__.py
azure/mgmt/containerservicesafeguards/_utils/model_base.py
azure/mgmt/containerservicesafeguards/_utils/serialization.py
azure/mgmt/containerservicesafeguards/aio/__init__.py
azure/mgmt/containerservicesafeguards/aio/_client.py
azure/mgmt/containerservicesafeguards/aio/_configuration.py
azure/mgmt/containerservicesafeguards/aio/_patch.py
azure/mgmt/containerservicesafeguards/aio/operations/__init__.py
azure/mgmt/containerservicesafeguards/aio/operations/_operations.py
azure/mgmt/containerservicesafeguards/aio/operations/_patch.py
azure/mgmt/containerservicesafeguards/models/__init__.py
azure/mgmt/containerservicesafeguards/models/_enums.py
azure/mgmt/containerservicesafeguards/models/_models.py
azure/mgmt/containerservicesafeguards/models/_patch.py
azure/mgmt/containerservicesafeguards/operations/__init__.py
azure/mgmt/containerservicesafeguards/operations/_operations.py
azure/mgmt/containerservicesafeguards/operations/_patch.py
azure_mgmt_containerservicesafeguards-1.0.0b1.dist-info/LICENSE
azure_mgmt_containerservicesafeguards-1.0.0b1.dist-info/METADATA
azure_mgmt_containerservicesafeguards-1.0.0b1.dist-info/WHEEL
azure_mgmt_containerservicesafeguards-1.0.0b1.dist-info/top_level.txt
azure_mgmt_containerservicesafeguards-1.0.0b1.dist-info/RECORD
